coman/__init__.py
coman/__main__.py
coman/_version.py
coman/cli.py
coman/env.py
coman/lock.py
coman/spec.py
coman/system.py
coman/utils.py
coman/commands/__init__.py
coman/commands/spec.py
coman/commands/utils.py
coman-0.1a5.dist-info/LICENSE
coman-0.1a5.dist-info/METADATA
coman-0.1a5.dist-info/WHEEL
coman-0.1a5.dist-info/entry_points.txt
coman-0.1a5.dist-info/top_level.txt
coman-0.1a5.dist-info/RECORD
