Metadata-Version: 2.1
Name: coman
Version: 0.1a5
Summary: Simpler Conda dependency management
Home-page: https://github.com/wietsedv/coman
Author: Wietse de Vries
Author-email: wietse.de.vries@rug.com
License: MIT
Platform: UNKNOWN
License-File: LICENSE
Requires-Dist: click (>=8.0.1)
Requires-Dist: ensureconda (>=1.4.1)
Requires-Dist: pip-tools (>=6.2.0)
Requires-Dist: ruamel.yaml (>=0.17.10)
Requires-Dist: shellingham (>=1.4.0)
Requires-Dist: semantic-version (>=2.8.5)
